LICENSE
MANIFEST.in
README.md
pyproject.toml
requirements.txt
setup.cfg
setup.py
stairmaze/__init__.py
stairmaze/checker.py
stairmaze/exceptions.py
stairmaze/cli/__init__.py
stairmaze/cli/app.py
stairmaze/cli/check.py
stairmaze/cli/prepare.py
stairmaze/transformers/__init__.py
stairmaze/transformers/dag2sfn_definition.py
stairmaze/transformers/task2job_definition.py
stairmaze/transformers/templates/job.json.template
stairmaze/transformers/templates/task.json.template
stairmaze/transformers/tools/__init__.py
stairmaze/transformers/tools/dag_reducer.py
stairmaze_cli.egg-info/PKG-INFO
stairmaze_cli.egg-info/SOURCES.txt
stairmaze_cli.egg-info/dependency_links.txt
stairmaze_cli.egg-info/entry_points.txt
stairmaze_cli.egg-info/requires.txt
stairmaze_cli.egg-info/top_level.txt