Metadata-Version: 2.1
Name: stairmaze-cli
Version: 0.1.4
Summary: Stairmaze cli
Home-page: 
Author: Emilio G. Ortiz García
Author-email: 
License: LICENSE
License-File: LICENSE
